petra_plaid_python-1.4.0.dist-info/DESCRIPTION.rst
petra_plaid_python-1.4.0.dist-info/METADATA
petra_plaid_python-1.4.0.dist-info/RECORD
petra_plaid_python-1.4.0.dist-info/WHEEL
petra_plaid_python-1.4.0.dist-info/metadata.json
petra_plaid_python-1.4.0.dist-info/top_level.txt
plaid/__init__.py
plaid/client.py
plaid/errors.py
plaid/http.py
plaid/requester.py
plaid/utils.py
plaid/version.py
tests/__init__.py
tests/integration/__init__.py
tests/integration/test_client.py
tests/unit/__init__.py
tests/unit/test_client.py
