Metadata-Version: 2.0
Name: petra-plaid-python
Version: 1.4.0
Summary: Simple Python API client for Plaid -- modified by Petra
Home-page: https://github.com/PetraFinance/plaid-python
Author: Arlan Jaska
Author-email: ajaska@trypetra.com
License: MIT
Download-URL: https://github.com/PetraFinance/plaid-python/tarball/v1.4.0
Keywords: api,client,plaid
Platform: UNKNOWN
Classifier: Programming Language :: Python
Classifier: Programming Language :: Python :: 2
Classifier: Programming Language :: Python :: 2.7
Classifier: Programming Language :: Python :: 3
Classifier: Programming Language :: Python :: 3.4
Classifier: Topic :: Software Development :: Libraries :: Python Modules
Classifier: Environment :: Web Environment
Requires-Dist: requests (>=2.7.0)
